hello.py
hellouser_bnb-0.0.1.dist-info/LICENSE.txt
hellouser_bnb-0.0.1.dist-info/METADATA
hellouser_bnb-0.0.1.dist-info/WHEEL
hellouser_bnb-0.0.1.dist-info/top_level.txt
hellouser_bnb-0.0.1.dist-info/RECORD
