Metadata-Version: 2.1
Name: hellouser-bnb
Version: 0.0.1
Summary: Hello User Module
Home-page: UNKNOWN
Author: Bhushan
Author-email: bhushan.bhupta@accenture.com
License: UNKNOWN
Platform: UNKNOWN
